skarv/__init__.py
skarv/concurrency.py
skarv/middlewares.py
skarv/utilities/__init__.py
skarv/utilities/zenoh.py
skarv-0.3.0.dist-info/licenses/LICENSE
skarv-0.3.0.dist-info/METADATA
skarv-0.3.0.dist-info/WHEEL
skarv-0.3.0.dist-info/top_level.txt
skarv-0.3.0.dist-info/RECORD
