Metadata-Version: 2.4
Name: skarv
Version: 0.3.0
Summary: A single process, in-memory message queue written in python.
Author-email: Fredrik Olsson <freol@outlook.com>
License-Expression: Apache-2.0
Requires-Python: >=3.10
License-File: LICENSE
Requires-Dist: eclipse-zenoh<2.0,>=1.0
Dynamic: license-file
